<?xml version="1.0" encoding="UTF-8"?>
<Spase xmlns="http://www.spase-group.org/data/schema" xmlns:xsi="http://www.w3.org/2001/XMLSchema-instance" xsi:schemaLocation="http://www.spase-group.org/data/schema http://www.spase-group.org/data/schema/spase-1_3_0.xsd">
    <Version>2.2.1</Version>
    <NumericalData>
        <ResourceID>spase://VSPO/NumericalData/THEMIS/Ground/UCLA-GBO/GAKO/MAG/PT0.5S</ResourceID>
        <ResourceHeader>
            <ResourceName>THEMIS Ground-based Vector Magnetic Field at Gakona, Alaska</ResourceName>
            <ReleaseDate>2011-11-15T00:00:00Z</ReleaseDate>
            <Description>GAKO is part of the UCLA GBO Network. This magnetometer was produced at UCLA.  It records 3-axis magnetic field measurements at 2Hz frequency.  Calibration files used are at: http://www-ssc.igpp.ucla.edu/themis_data/calib_files/</Description>
            <Acknowledgement>We acknowledge NASA contract NAS5-02099 and V. Angelopoulos for use of data from the THEMIS Mission. Specifically:S. Mende and C. T. Russell for use of the data</Acknowledgement>
            <Contact>
                <PersonID>spase://SMWG/Person/Vassilis.Angelopoulos</PersonID>
                <Role>PrincipalInvestigator</Role>
            </Contact>
            <Contact>
                <PersonID>spase://SMWG/Person/Christopher.T.Russell</PersonID>
                <Role>CoInvestigator</Role>
            </Contact>
            <Contact>
                <PersonID>spase://SMWG/Person/Stephen.B.Mende</PersonID>
                <Role>CoInvestigator</Role>
            </Contact>
            <InformationURL>
                <Name>THEMIS Ground Magnetometer Data Center at UCLA</Name>
                <URL>http://spc.igpp.ucla.edu/uclamag/themis_center/</URL>
                <Description>Web server for displaying and downloading THEMIS ground magnetometer data</Description>
            </InformationURL>
            <InformationURL>
                <Name>THEMIS Web site ground magnetometer page.</Name>
                <URL>http://themis.ssl.berkeley.edu/instrument_gmags.shtml</URL>
                <Description>THEMIS Web Site page on ground magnetometers. Contains links to papers, general purpose information and caveats.</Description>
            </InformationURL>
        </ResourceHeader>
    <AccessInformation>
      <RepositoryID>spase://SMWG/Repository/NASA/GSFC/SPDF</RepositoryID>
      <Availability>Online</Availability>
      <AccessRights>Open</AccessRights>
      <AccessURL>
        <Name>CDAWeb ftp area</Name>
       <URL>ftp://cdaweb.gsfc.nasa.gov/pub/istp/themis/thg/l2/mag/gako/</URL>
        <Description>For ftp retrieval of daily CDF files</Description>
      </AccessURL>
      <Format>CDF</Format>
      <Acknowledgement>Please acknowledge Vassilis Angelopoulos,THEMIS mission Principal Investigator, and the CDAWeb team at GSFC/SPDF.</Acknowledgement>
    </AccessInformation>
    <AccessInformation>
      <RepositoryID>spase://SMWG/Repository/NASA/GSFC/SPDF</RepositoryID>
      <Availability>Online</Availability>
      <AccessRights>Open</AccessRights>
      <AccessURL>
        <Name>CDAWeb</Name>
        <URL>http://cdaweb.gsfc.nasa.gov/sp_phys/</URL>
        <Description>Access to ASCII, CDF, and plots via NASA/GSFC CDAWeb</Description>
      </AccessURL>
      <Format>Text</Format>
      <Acknowledgement>Please acknowledge Vassilis Angelopoulos,THEMIS mission Principal Investigator, and the CDAWeb team at GSFC/SPDF.</Acknowledgement>
    </AccessInformation>
        <ProcessingLevel>Calibrated</ProcessingLevel>
        <InstrumentID>spase://SMWG/Instrument/THEMIS/Ground/UCLA-GBO/GAKO/MAG</InstrumentID>
        <MeasurementType>MagneticField</MeasurementType>
        <TemporalDescription>
            <TimeSpan>
                <StartDate>2006-01-01T00:00:00</StartDate>
                <RelativeStopDate>-P180D</RelativeStopDate>
            </TimeSpan>
        </TemporalDescription>
        <ObservedRegion>Earth.Surface</ObservedRegion>
       </NumericalData>
</Spase>


