<Spase xmlns="http://www.spase-group.org/data/schema">
    <Version>2.2.0</Version>
    <NumericalData>
        <ResourceID>spase://VSPO/NumericalData/P_RHESSI_HDR_MULTIDS</ResourceID>
        <ResourceHeader>
            <ResourceName>RHESSI data, multiple products</ResourceName>
            <ReleaseDate>2007-06-01T00:00:00</ReleaseDate>
            <Description>RHESSI digital and display image and spectral data, count rates and light curves, 3 keV X rays to 17 MeV gamma rays, from multiple RHESSI sites</Description>
            <Contact>
                <PersonID>spase://SMWG/Person/Robert.P.Lin</PersonID>             <!-- see also http://hesperia.gsfc.nasa.gov/hessi/hessi_team.htm -->
                <Role>PrincipalInvestigator</Role>
            </Contact>
        </ResourceHeader>
        <AccessInformation>
            <RepositoryID>spase://SMWG/Repository/UCB</RepositoryID>
            <Availability>Online</Availability>
            <AccessRights>Open</AccessRights>
            <AccessURL>
                <Name>RHESSI Data and Software Center at UC, Berkeley</Name>
                <URL>http://rhessidatacenter.ssl.berkeley.edu/</URL>
            </AccessURL>
            <AccessURL>
                <Name>RHESSI Data and Software Center at NASA/GSFC</Name>
                <URL>http://hesperia.gsfc.nasa.gov/rhessidatacenter/</URL>
            </AccessURL>
            <AccessURL>
                <Name>HESSI Experimental Data Center at ETH, Zurich</Name>
                <URL>http://www.hessi.ethz.ch/</URL>
            </AccessURL>
            <AccessURL>
                <Name>from GSFC/LSSP via Virtual Solar Observatory</Name>
                <URL>http://www.virtualsolar.org/</URL>
            </AccessURL>
            <Format>FITS</Format>         <!-- &amp;amp;lt;Format&amp;amp;gt;Text&amp;amp;lt;/Format&amp;amp;gt; -->
        </AccessInformation>
        <ProviderProcessingLevel>UNCALIBRATED</ProviderProcessingLevel>
        <InstrumentID>spase://SMWG/Instrument/RHESSI/HESSI</InstrumentID>
        <MeasurementType>ImageIntensity</MeasurementType>
        <MeasurementType>Spectrum</MeasurementType>
        <TemporalDescription>
            <TimeSpan>
                <StartDate>2002-02-07T00:00:00</StartDate>
                <RelativeStopDate>-P1D</RelativeStopDate>
                <Note>Most data are current to within a day or so.</Note>
            </TimeSpan>
            <Cadence>PT0.1S</Cadence>
        </TemporalDescription>      <!--InstrumentRegion=Heliosphere.NearEarth-->
        <ObservedRegion>Sun</ObservedRegion>
        <ObservedRegion>Sun.Chromosphere</ObservedRegion>
        <ObservedRegion>Sun.Photosphere</ObservedRegion>
    </NumericalData>
</Spase>
