<?xml version="1.0" encoding="UTF-8"?>
<Spase xmlns="http://www.spase-group.org/data/schema">
  <Version>2.0.1</Version>
  <Service>
    <ResourceID>spase://VSPO/Service/P_CCMC_HDR_MAGNSPH_RUN</ResourceID>
    <ResourceHeader>
      <ResourceName>CCMC: Magnetospheric Models</ResourceName>
      <ReleaseDate>2007-03-05T00:00:00Z</ReleaseDate>
      <Description>Run magnetospheric models (BATSRUS, UCLA-GGCM) at CCMC</Description>
      <Contact>
        <PersonID>spase://SMWG/Person/Masha.Kuznetsova</PersonID>
        <Role>GeneralContact</Role>
      </Contact>
      <Contact>
        <PersonID>spase://SMWG/Person/Tamas.I.Gombosi</PersonID>
        <!-- BATSRUS -->
        <Role>GeneralContact</Role>
      </Contact>
      <Contact>
        <PersonID>spase://SMWG/Person/Jimmy.Raeder</PersonID>
        <!-- UCLA-GGCM -->
        <Role>GeneralContact</Role>
      </Contact>
      <InformationURL>
        <Name>CCMC top page</Name>
        <URL>http://ccmc.gsfc.nasa.gov/</URL>
      </InformationURL>
    </ResourceHeader>
    <AccessURL>
      <Name>CCMC executable magnetospheric models page</Name>
      <URL>http://ccmc.gsfc.nasa.gov/models/models_at_glance.php</URL>
    </AccessURL>
    <!--      &amp;amp;amp;lt;MeasurementType&amp;amp;amp;gt;ThermalPlasma&amp;amp;amp;lt;/MeasurementType&amp;amp;amp;gt;      &amp;amp;amp;lt;MeasurementType&amp;amp;amp;gt;MagneticField&amp;amp;amp;lt;/MeasurementType&amp;amp;amp;gt;      &amp;amp;amp;lt;ObservedRegion&amp;amp;amp;gt;Earth.Magnetosphere&amp;amp;amp;lt;/ObservedRegion&amp;amp;amp;gt;      &amp;amp;amp;lt;ObservedRegion&amp;amp;amp;gt;Earth.NearSurface.Ionosphere&amp;amp;amp;lt;/ObservedRegion&amp;amp;amp;gt;      &amp;amp;amp;lt;INSTRUMENT_ABBREVIATION&amp;amp;amp;gt;BATSRUS&amp;amp;amp;lt;/INSTRUMENT_ABBREVIATION&amp;amp;amp;gt;      &amp;amp;amp;lt;INSTRUMENT_ABBREVIATION&amp;amp;amp;gt;UCLA-GGCM&amp;amp;amp;lt;/INSTRUMENT_ABBREVIATION&amp;amp;amp;gt;      &amp;amp;amp;lt;INSTRUMENT_ABBREVIATION&amp;amp;amp;gt;BATSRUS&amp;amp;amp;lt;/INSTRUMENT_ABBREVIATION&amp;amp;amp;gt;      &amp;amp;amp;lt;INSTRUMENT_ABBREVIATION&amp;amp;amp;gt;UCLA-GGCM&amp;amp;amp;lt;/INSTRUMENT_ABBREVIATION&amp;amp;amp;gt;      -->
  </Service>
</Spase>
